icc/__init__.py
icc/models.py
python_icc-0.0.28.dist-info/METADATA
python_icc-0.0.28.dist-info/WHEEL
python_icc-0.0.28.dist-info/top_level.txt
python_icc-0.0.28.dist-info/RECORD
